{
    "enclosure:fru:controller":[
        {
            "alert_type":"fault",
            "severity":"critical",
            "action":"failed"
        },
        {
            "alert_type":"fault_resolved",
            "severity":"informational",
            "action":"resolved"
        },
        {
            "alert_type":"missing",
            "severity":"critical",
            "action":"failed"
        },
        {
            "alert_type":"insertion",
            "severity":"informational",
            "action":"resolved"
        }
    ],
    "node:interface:nw":[
        {
            "alert_type":"fault",
            "severity":"warning",
            "action":"failed"
        },
        {
            "alert_type":"fault_resolved",
            "severity":"informational",
            "action":"resolved"
        }
    ],
    "node:interface:nw:cable":[
        {
            "alert_type":"fault",
            "severity":"warning",
            "action":"failed"
        },
        {
            "alert_type":"fault_resolved",
            "severity":"informational",
            "action":"resolved"
        }
    ],
    "iem":[
        {
            "alert_type":"fault",
            "severity":"alert",
            "component_id":"auth",
            "module_id":"LDAP",
            "action":"restart"
        }
    ],
    "node:interface:sas":[
        {
            "alert_type":"fault",
            "severity":"critical",
            "action":"failed"
        },
        {
            "alert_type":"fault_resolved",
            "severity":"informational",
            "action":"resolved"
        }
    ]
}